scalum/__init__.py
scalum/Scale.py
scalum/ScaleWithInverse.py
scalum/ScaleWithPaddingMap.py
scalum/ScaleWithPolyAnnotation.py
scalum/ScaleWithYoloAnnotation.py
scalum-1.3.2.dist-info/WHEEL
scalum-1.3.2.dist-info/METADATA
scalum-1.3.2.dist-info/RECORD
